{
    "patient_id": "history_physical_3",
    "raw_text": "Gender: Female\n\nAge: 65\n\nMRN: 775170\n\nDiagnosis: Chronic viral hepatitis C\n\nHistory and Physical:\n\nFirst Visit  28th June 2024\n\nDoctor: Hello, how are you feeling today? What brings you here?\n\nPatient: Doctor, I have been feeling very weak lately.\n\nDoctor: I see. Have you noticed any other symptoms?\n\nPatient: Yes, Ive had swelling in both my legs and abdominal distension since 2019. Recently, I also\n\nhad black-colored stool (melena).\n\nDoctor: That sounds concerning. Do you have any history of liver disease or hepatitis?\n\nPatient:  Yes,  I  was  diagnosed  with  hepatitis  B  in  2019  and  took  treatment  for  three  months.  After\n\nthat, I was managing my condition with medications.\n\nDoctor: Understood. Have you had any episodes of vomiting blood (hematemesis) or jaundice?\n\nPatient: No, I haven't had hematemesis or jaundice, but I do have ascites that responds to diuretics.\n\nDoctor: Have you had significant weight loss, fevers, or night sweats?\n\nPatient: No, none of those.\n\nDoctor: Have you ever needed a blood transfusion?\n\nPatient: Yes, Ive had five pints of blood transfused.\n\nDoctor: I see. What medications are you currently taking?\n\nPatient:  I  take  Cap  Nexum  40mg,  Tab  Spiromide  40mg,  Tab  Carveda  3.125mg,  and  Tab  Rifaxa\n\n550mg.\n\nDoctor: Thank you for sharing that. Now, let me examine you. [Performs examination]\n\n(cid:9)CNS: Conscious, well-oriented (GCS 15/15)\n\n(cid:9)CVS: Normal heart sounds (S1 + S2 + 0)\n\n(cid:9)Respiratory: Normal breath sounds (bilateral vesicular breathing)\n\n\f(cid:9)GIT: Abdomen soft, non-tender, non-distended\n\nDoctor: Lets review your test results.\n\nInvestigations:\n\n(cid:9)Endoscopy  (04/05/24):  Three  small  columns  of  esophageal  varices  (EV)  without  recent  bleeding,\n\nsevere pangastritis with multiple nodules and ulcers, portal hypertension.\n\n(cid:9)Ultrasound  Abdomen  (03/06/24):  Cirrhotic  liver,  portal  hypertension,  mild  to  moderate  ascites,  no\n\nfocal lesions.\n\n(cid:9)CT  Scan  (10/06/24):  Cirrhotic  liver  with  left  lobe  hypertrophy,  no  arterialized  lesions,  portal  vein\n\nthrombosis, moderate splenomegaly.\n\nLab Results:\n\nTest(cid:9)22/03/24(cid:9)07/06/24\n\nHemoglobin (HB)(cid:9)8.7(cid:9)-\n\nTLC(cid:9)6.3(cid:9)-\n\nPlatelets (PLT)(cid:9)64(cid:9)-\n\nTotal Bilirubin (T-BIL)(cid:9)-(cid:9)0.8\n\nALT/AST(cid:9)-(cid:9)23/25\n\nALP(cid:9)-(cid:9)75\n\nAlbumin(cid:9)-(cid:9)3.5\n\nCreatinine(cid:9)1.27(cid:9)1.03\n\nSodium (Na)(cid:9)125(cid:9)-\n\nPotassium (K)(cid:9)4.1(cid:9)-\n\nINR(cid:9)-(cid:9)1.1\n\nAFP(cid:9)-(cid:9)1.9\n\nPIVKA II(cid:9)-(cid:9)31.77\n\nMELD Na Score(cid:9)-(cid:9)8 points\n\nDoctor:  Based  on  your  history,  examination,  and  tests,  we  suspect  Hepatitis  B  or  C-related\n\ndecompensated chronic liver disease (DCLD).\n\n\fPatient: Whats the next step, doctor?\n\nDoctor:  We  need  to  complete  your  HBV  and  HCV  PCR  tests.  Liver  transplant  is  the  definitive\n\ntreatment,  but  its  not  immediately  necessary.  Your  son  is  available  as  a  donor,  and  we  have\n\nexplained the donor criteria to him. We will monitor your condition closely.\n\nManagement Plan:\n\n1.(cid:9)Complete pending lab tests (HBV and HCV PCR).\n\n2.(cid:9)Submit a CD of the CT scan to Interventional Radiology.\n\n3.(cid:9)Follow up with hepatology in three weeks.\n\n4.(cid:9)Start Qalsan D once daily.\n\nFollow-up Visit  11th October 2024\n\nDoctor: Welcome back. Have you had any new symptoms since your last visit?\n\nPatient: Yes, I have been experiencing nausea and loose stools.\n\nDoctor: I see. Let me confirmare you still taking your medications?\n\nPatient: Yes, I am currently taking:\n\n(cid:9)Spironolactone/furosemide 20/50mg\n\n(cid:9)Iron tablets (Fefol)\n\n(cid:9)Qalsan (Vitamin D)\n\n(cid:9)Carvedilol 3.125mg twice daily\n\n(cid:9)Ensure (nutritional supplement) three times daily\n\n(cid:9)Omeprazole 40mg\n\nDoctor: Let's do a quick examination.\n\n(cid:9)General Appearance: Normal-looking, middle-aged woman\n\n(cid:9)CNS: Alert and oriented (GCS 15/15)\n\n(cid:9)CVS: Normal heart sounds (S1 + S2 + 0)\n\n(cid:9)GIT: Soft, non-tender abdomen\n\n(cid:9)Respiratory: Normal breath sounds\n\n\fInvestigations:\n\n(cid:9)Ultrasound  Abdomen  (29/06/24):  Chronic  liver  disease  with  moderate  splenomegaly,  mild  ascites,\n\nno discrete focal hepatic lesions.\n\n(cid:9)CT  Scan  (29/06/24):  Bland  thrombus  in  the  portal  vein,  dilated  portal  and  splenic  veins,  bilateral\n\nrenal cysts.\n\nLab Results:\n\nTest(cid:9)22/03/24(cid:9)07/06/24(cid:9)24/08/24\n\nHemoglobin (HB)(cid:9)8.7(cid:9)-(cid:9)9.1\n\nTLC(cid:9)6.3(cid:9)-(cid:9)14.5\n\nPlatelets (PLT)(cid:9)64(cid:9)-(cid:9)58,000\n\nTotal Bilirubin (T-BIL)(cid:9)-(cid:9)0.8(cid:9)1.2\n\nALT/AST(cid:9)-(cid:9)23/25(cid:9)41\n\nALP(cid:9)-(cid:9)75(cid:9)79\n\nAlbumin(cid:9)-(cid:9)3.5(cid:9)-\n\nCreatinine(cid:9)1.27(cid:9)1.03(cid:9)1.13\n\nSodium (Na)(cid:9)125(cid:9)-(cid:9)132\n\nPotassium (K)(cid:9)4.1(cid:9)-(cid:9)4.67\n\nINR(cid:9)-(cid:9)1.1(cid:9)1.28\n\nAFP(cid:9)-(cid:9)1.9(cid:9)-\n\nPIVKA II(cid:9)-(cid:9)31.77(cid:9)-\n\nMELD Na Score(cid:9)-(cid:9)8 points(cid:9)8 points\n\nDoctor:  Your  condition  remains  stable,  but  there  is  some  confusion  about  whether  you  have\n\nHepatitis B or C. We need further testing to confirm.\n\nPatient: What should I do next?\n\nDoctor: Heres the plan:\n\n1.(cid:9)Colonoscopy to evaluate chronic diarrhea.\n\n2.(cid:9)HBsAg, AFP, and HCV PCR to clarify hepatitis status.\n\n\f3.(cid:9)Ultrasound abdomen and plan an endoscopy.\n\n4.(cid:9)Medications:\n\no(cid:9)Spironolactone 100mg once daily\n\no(cid:9)Calcium carbonate/Vitamin D once daily\n\no(cid:9)Carvedilol 3.125mg twice daily\n\no(cid:9)Multivitamin once daily\n\n5.(cid:9)Follow-up in six weeks.\n\nDoctor: If you experience worsening symptoms, please return earlier.\n\nPatient: Thank you, doctor.\n\n\f",
    "structured_data": {
        "PatientDemographics": {
            "Gender": "Female",
            "Age": "65",
            "MRN": "775170",
            "Diagnosis": "Chronic viral hepatitis C"
        },
        "ClinicalSummary": {
            "ActiveSymptoms": [
                "Weakness",
                "Swelling in both legs",
                "Abdominal distension",
                "Black-colored stool",
                "Nausea",
                "Loose stools"
            ],
            "NegativeFindings": [
                "No hematemesis",
                "No jaundice",
                "No significant weight loss",
                "No fevers",
                "No night sweats"
            ]
        },
        "DiagnosticConclusions": [
            "Hepatitis B or C-related decompensated chronic liver disease (DCLD)"
        ],
        "TherapeuticInterventions": {
            "Medications": [
                "Cap Nexum 40mg",
                "Tab Spiromide 40mg",
                "Tab Carveda 3.125mg",
                "Tab Rifaxa 550mg",
                "Spironolactone/furosemide 20/50mg",
                "Iron tablets (Fefol)",
                "Qalsan (Vitamin D)",
                "Carvedilol 3.125mg twice daily",
                "Ensure (nutritional supplement) three times daily",
                "Omeprazole 40mg",
                "Spironolactone 100mg once daily",
                "Calcium carbonate/Vitamin D once daily",
                "Multivitamin once daily"
            ],
            "Procedures": [
                "Endoscopy",
                "Colonoscopy"
            ]
        },
        "DiagnosticEvidence": {
            "ImagingFindings": [
                "Endoscopy: Three small columns of esophageal varices without recent bleeding, severe pangastritis with multiple nodules and ulcers, portal hypertension",
                "Ultrasound Abdomen: Cirrhotic liver, portal hypertension, mild to moderate ascites, no focal lesions",
                "CT Scan: Cirrhotic liver with left lobe hypertrophy, no arterialized lesions, portal vein thrombosis, moderate splenomegaly",
                "Ultrasound Abdomen: Chronic liver disease with moderate splenomegaly, mild ascites, no discrete focal hepatic lesions",
                "CT Scan: Bland thrombus in the portal vein, dilated portal and splenic veins, bilateral renal cysts"
            ],
            "LabResults": [
                {
                    "Test": "Hemoglobin (HB)",
                    "Results": [
                        "8.7",
                        "-",
                        "9.1"
                    ]
                },
                {
                    "Test": "TLC",
                    "Results": [
                        "6.3",
                        "-",
                        "14.5"
                    ]
                },
                {
                    "Test": "Platelets (PLT)",
                    "Results": [
                        "64",
                        "-",
                        "58,000"
                    ]
                },
                {
                    "Test": "Total Bilirubin (T-BIL)",
                    "Results": [
                        "-",
                        "0.8",
                        "1.2"
                    ]
                },
                {
                    "Test": "ALT/AST",
                    "Results": [
                        "-",
                        "23/25",
                        "41"
                    ]
                },
                {
                    "Test": "ALP",
                    "Results": [
                        "-",
                        "75",
                        "79"
                    ]
                },
                {
                    "Test": "Albumin",
                    "Results": [
                        "-",
                        "3.5",
                        "-"
                    ]
                },
                {
                    "Test": "Creatinine",
                    "Results": [
                        "1.27",
                        "1.03",
                        "1.13"
                    ]
                },
                {
                    "Test": "Sodium (Na)",
                    "Results": [
                        "125",
                        "-",
                        "132"
                    ]
                },
                {
                    "Test": "Potassium (K)",
                    "Results": [
                        "4.1",
                        "-",
                        "4.67"
                    ]
                },
                {
                    "Test": "INR",
                    "Results": [
                        "-",
                        "1.1",
                        "1.28"
                    ]
                },
                {
                    "Test": "AFP",
                    "Results": [
                        "-",
                        "1.9",
                        "-"
                    ]
                },
                {
                    "Test": "PIVKA II",
                    "Results": [
                        "-",
                        "31.77",
                        "-"
                    ]
                },
                {
                    "Test": "MELD Na Score",
                    "Results": [
                        "-",
                        "8 points",
                        "8 points"
                    ]
                }
            ],
            "PathologyFindings": []
        },
        "ChronicConditions": {
            "ChronicDiseases": [
                "Chronic viral hepatitis C",
                "Chronic liver disease"
            ],
            "Comorbidities": [
                "Hepatitis B"
            ]
        },
        "Follow-upPlan": {
            "PlannedConsultations": [
                "Hepatology"
            ],
            "ScheduledTests": [
                "HBV and HCV PCR",
                "Colonoscopy",
                "HBsAg",
                "AFP",
                "HCV PCR",
                "Ultrasound abdomen",
                "Endoscopy"
            ],
            "NextAppointmentDetails": [
                "Follow-up in three weeks",
                "Follow-up in six weeks"
            ]
        },
        "VisitTimeline": [
            {
                "Date": "28th June 2024",
                "VisitType": "First Visit"
            },
            {
                "Date": "11th October 2024",
                "VisitType": "Follow-up Visit"
            }
        ],
        "SummaryNarrative": {
            "ClinicalCourseProgression": "Patient has been experiencing weakness, swelling in legs, abdominal distension, and black-colored stool since 2019.",
            "DiagnosticJourney": "Patient diagnosed with hepatitis B in 2019, currently suspected of having hepatitis C-related decompensated chronic liver disease.",
            "TreatmentResponse": "Patient is on multiple medications and has had blood transfusions.",
            "OngoingConcerns": "Need for further testing to confirm hepatitis status and monitor liver condition."
        }
    }
}