{
    "patient_id": "history_physical_42",
    "raw_text": "Gender: Male\n\nAge: 65\n\nMRN: 771711\n\nDiagnosis: Cholangiocarcinoma\n\nHistory and Physical:\n\nDate: 4th June 2024\n\nDepartment: HPB & Liver Transplant (LTx)\n\nDoctor: Hello, what brings you in today?\n\nPatient: I've been having pain in the right upper part of my abdomen for the past two months. And I\n\ndeveloped jaundice about a month ago.\n\nDoctor: I see. Any past medical conditions?\n\nPatient: I was diagnosed with Hepatitis C back in 2008. I took treatment with direct-acting antivirals,\n\nand I achieved SVR. My last HCV PCR was done on 28th January 2023, and it was negative.\n\nDoctor:  Okay.  Let  me  ask  a  few  questions  to  assess  your  general  condition.  Have  you  had  any\n\nvomiting of blood, or signs of decompensation like fluid accumulation?\n\nPatient: No hematemesis or ascites. But I did have black stools around two months ago.\n\nDoctor: Any signs of confusion or forgetfulness?\n\nPatient: No, nothing like that.\n\n\fDoctor: Any weight changes recently?\n\nPatient: Yes, Ive lost about 3 kilograms in the past three months.\n\nDoctor: Fever? Night sweats?\n\nPatient: No.\n\nDoctor: Any previous surgeries or allergies?\n\nPatient: No surgeries, and no known allergies.\n\nDoctor: What medications are you taking currently?\n\nPatient: None at the moment.\n\nDoctor: Okay. Any family history of diabetes, hypertension, cancer, TB, or asthma?\n\nPatient: Nothing significant.\n\nDoctor: Whats your current lifestyle like?\n\nPatient: I stay at home. Ive been smoking hookah and cigarettes for around 40 years.\n\nDoctor: Financially, is everything okay?\n\nPatient: There are some financial strains, but we manage.\n\n\fDoctor: Any mental health concerns? Feeling low or depressed?\n\nPatient: No, I'm mentally okay. No suicidal thoughts or self-harm history.\n\nDoctor: Do you have any spiritual or cultural preferences we should be aware of during your care?\n\nPatient: No, nothing specific.\n\nDoctor: Any issues with language, speech, vision, memory, or mobility?\n\nPatient: None.\n\nSystemic Examination:\n\nCNS: Patient is conscious and well oriented. GCS is 15/15.\n\nCVS: S1 and S2 heart sounds are present, no added sounds.\n\nGIT: Abdomen is soft, non-tender, and non-distended.\n\nInvestigations:\n\nCT Scan (08-Apr-24):\n\nHepatomegaly\n\nIll-defined isodense lesion (1.9 x 2.3 cm) at the confluence of hepatic ducts\n\n\fAbrupt narrowing of right and left hepatic ducts\n\nIntrahepatic biliary dilatation\n\nAnother hypodense lesion (3.1 x 2.5 cm) in segment VI\n\nMRI Liver (27-May-24):\n\nLesion at CHD (1.5 x 1.4 x 2.08 cm), extending into segments IV.b, VI, VII\n\nAnother lesion (0.87 x 1.01 cm) in segment V\n\nLab Results (26-May-24):\n\nHemoglobin: 14.4\n\nTLC: 5.9\n\nPlatelets: 170\n\nTotal Bilirubin: 4.6\n\nALT/AST: 157\n\nAlbumin: 4.3\n\nCreatinine: 0.83\n\n\fSodium: 137\n\nPotassium: 3.8\n\nINR: 1\n\nChild-Turcotte-Pugh (CTP): B7\n\nMELD-Na Score: 12\n\nCA 19-9: 22\n\nCEA: 2.6\n\nAFP (4-Apr-24): 155\n\nECOG performance status: 0\n\nBMI: 18.5\n\nDiagnosis:\n\nKlatskin tumor with extension into segments IV.b, VI, VII\n\nPlan:\n\nRepeat CT scan to assess resectability\n\nRepeat labs\n\n\fQuit smoking and perform spirometry\n\nLiver biopsy of left lobe (refer to IR)\n\nCounselling regarding risks (resectability, mortality, morbidity)\n\nReferral to financial support\n\nFollow-Up Visit\n\nDate: 24th June 2024\n\nDoctor: Welcome back. How are you feeling since the last visit?\n\nPatient: I still have the pain in my right side, jaundice is persistent, and now I feel generally weak.\n\nDoctor:  Okay.  Lets  revisit  your  background.  You  had  HCV  diagnosed  in  2008,  were  treated  and\n\nachieved SVR, correct?\n\nPatient: Yes.\n\nDoctor: Any new symptoms or issues since the last visit?\n\nPatient: No new symptoms. Still no fever, night sweats, or any bleeding. My weight is still down by 3\n\nkg.\n\nDoctor: Lets go through your investigations.\n\n\fUpdated Imaging:\n\nTriphasic CT Scan (20-Jun-24):\n\nProgressively enhancing intraluminal growth involving CHD\n\nInvolvement of ductal confluence, right posterior duct system up to subsegmental branches\n\nProximal segment IV duct also involved\n\nVascular encasement and retrograde bilobar biliary dilatation\n\nArterially enhancing segment V focus with washout (suggestive of HCC lesion)\n\nMild hepatic cirrhosis\n\nSuspicious porta hepatis nodes\n\nLiver Biopsy (04-Jun-24):\n\nMarked portal mixed acute and chronic inflammation\n\nAcute cholangitis and fibrous portal expansion\n\nDuctular proliferation, hepatocyte cholestasis, bile infarcts\n\nFocal lobular inflammation\n\n\fNo steatosis, granuloma, or malignancy\n\nMETAVIR Score: A3/F2\n\nUpdated Lab Results (22-Jun-24):\n\nTotal Bilirubin:  13.9 (from 4.6)\n\nALT/AST: 137 / 192\n\nALP: 660\n\n(Other labs unchanged from previous)\n\nAssessment:\n\nHilar Cholangiocarcinoma with extension into segment IV\n\nManagement Plan:\n\nProceed with ERCP and drainage of left ductal system\n\nConsider right liver lobe resection if feasible\n\nIf ERCP not successful, perform PTBD for left ductal system\n\nDiscuss case in Multidisciplinary Team (MDT) for staging and plan\n\nDecision between resection vs. TACE + Chemotherapy after MDT\n\n\fPatient and family counselled in detail about both options\n\nPrescriptions:\n\nTab Motilium\n\nSyp Mosegar\n\nSurbex-Z\n\nNext Visit\n\nDate: 3rd July 2024\n\nDepartment: Hepatology\n\nDoctor: Dr. Ahmad\n\n(To be continued...)\n\n\f",
    "structured_data": {
        "PatientDemographics": {
            "Gender": "Male",
            "Age": "65",
            "MRN": "771711",
            "Diagnosis": "Cholangiocarcinoma"
        },
        "ClinicalSummary": {
            "ActiveSymptoms": [
                "Pain in the right upper part of abdomen",
                "Jaundice",
                "General weakness"
            ],
            "NegativeFindings": [
                "No hematemesis",
                "No ascites",
                "No signs of confusion",
                "No fever",
                "No night sweats",
                "No new symptoms since last visit"
            ]
        },
        "DiagnosticConclusions": [
            "Klatskin tumor with extension into segments IV.b, VI, VII",
            "Hilar Cholangiocarcinoma with extension into segment IV"
        ],
        "TherapeuticInterventions": {
            "Medications": [
                "Tab Motilium",
                "Syp Mosegar",
                "Surbex-Z"
            ],
            "Procedures": [
                "Liver biopsy of left lobe",
                "ERCP and drainage of left ductal system",
                "Consider right liver lobe resection",
                "PTBD for left ductal system if ERCP not successful"
            ]
        },
        "DiagnosticEvidence": {
            "ImagingFindings": [
                "CT Scan: Hepatomegaly, ill-defined isodense lesion at confluence of hepatic ducts, abrupt narrowing of right and left hepatic ducts, intrahepatic biliary dilatation, hypodense lesion in segment VI",
                "MRI Liver: Lesion at CHD extending into segments IV.b, VI, VII, another lesion in segment V",
                "Triphasic CT Scan: Progressively enhancing intraluminal growth involving CHD, involvement of ductal confluence, vascular encasement, mild hepatic cirrhosis, suspicious porta hepatis nodes"
            ],
            "LabResults": [
                "Hemoglobin: 14.4",
                "TLC: 5.9",
                "Platelets: 170",
                "Total Bilirubin: 4.6",
                "ALT/AST: 157",
                "Albumin: 4.3",
                "Creatinine: 0.83",
                "Sodium: 137",
                "Potassium: 3.8",
                "INR: 1",
                "CA 19-9: 22",
                "CEA: 2.6",
                "AFP: 155",
                "Total Bilirubin: 13.9",
                "ALT/AST: 137 / 192",
                "ALP: 660"
            ],
            "PathologyFindings": [
                "Marked portal mixed acute and chronic inflammation",
                "Acute cholangitis and fibrous portal expansion",
                "Ductular proliferation, hepatocyte cholestasis, bile infarcts",
                "Focal lobular inflammation",
                "No steatosis, granuloma, or malignancy"
            ]
        },
        "ChronicConditions": {
            "ChronicDiseases": [
                "Hepatitis C"
            ],
            "Comorbidities": [
                "None"
            ]
        },
        "Follow-upPlan": {
            "PlannedConsultations": [
                "Multidisciplinary Team (MDT) for staging and plan"
            ],
            "ScheduledTests": [
                "Repeat CT scan",
                "Repeat labs"
            ],
            "NextAppointmentDetails": [
                "3rd July 2024"
            ]
        },
        "VisitTimeline": [
            {
                "Date": "4th June 2024",
                "Department": "HPB & Liver Transplant (LTx)"
            },
            {
                "Date": "24th June 2024",
                "Department": "Hepatology"
            },
            {
                "Date": "3rd July 2024",
                "Department": "Hepatology"
            }
        ],
        "SummaryNarrative": {
            "ClinicalCourseProgression": "Patient has persistent pain and jaundice, with weight loss.",
            "DiagnosticJourney": "Initial diagnosis of cholangiocarcinoma confirmed with imaging and biopsy.",
            "TreatmentResponse": "Patient has not shown improvement in symptoms since last visit.",
            "OngoingConcerns": "Management of cholangiocarcinoma and associated symptoms."
        }
    }
}